{
  "path": "sandbox/1782159197012-comments-integration.md-stress",
  "comments": [
    {
      "id": "stress-0",
      "authorEmail": "test@test.com",
      "authorName": "Integration Test",
      "body": "Stress test comment 0",
      "createdAt": "2026-06-22T20:13:30.736Z",
      "resolved": false,
      "parentId": null,
      "blockId": null,
      "lineNumber": null
    },
    {
      "id": "stress-2",
      "authorEmail": "test@test.com",
      "authorName": "Integration Test",
      "body": "Stress test comment 2",
      "createdAt": "2026-06-22T20:13:30.736Z",
      "resolved": false,
      "parentId": null,
      "blockId": null,
      "lineNumber": null
    },
    {
      "id": "stress-3",
      "authorEmail": "test@test.com",
      "authorName": "Integration Test",
      "body": "Stress test comment 3",
      "createdAt": "2026-06-22T20:13:30.736Z",
      "resolved": false,
      "parentId": null,
      "blockId": null,
      "lineNumber": null
    }
  ]
}